MANIFEST.in
README
requirements.txt
setup.py
bigpanda/__init__.py
bigpanda/alert.py
bigpanda/client.py
bigpanda/config.py
bigpanda/deployment.py
bigpanda.egg-info/PKG-INFO
bigpanda.egg-info/SOURCES.txt
bigpanda.egg-info/dependency_links.txt
bigpanda.egg-info/requires.txt
bigpanda.egg-info/top_level.txt