Metadata-Version: 1.0
Name: bigpanda
Version: 2.1
Summary: Python module for integration with BigPanda
Home-page: bigpanda.io
Author: BigPanda
Author-email: support@bigpanda.io
License: UNKNOWN
Platform: UNKNOWN
